nsedt/__init__.py
nsedt/equity.py
nsedt/indices.py
nsedt/reports.py
nsedt/derivatives/__init__.py
nsedt/derivatives/futures.py
nsedt/derivatives/options.py
nsedt/resources/__init__.py
nsedt/resources/constants.py
nsedt/resources/index_symbol.py
nsedt/utils/__init__.py
nsedt/utils/data_format.py
nsedt/utils/exceptions.py
nsedt-0.0.16.dist-info/licenses/LICENSE
nsedt-0.0.16.dist-info/METADATA
nsedt-0.0.16.dist-info/WHEEL
nsedt-0.0.16.dist-info/top_level.txt
nsedt-0.0.16.dist-info/RECORD
