Metadata-Version: 2.4
Name: nsedt
Version: 0.0.16
Summary: Library to collect NSE data
Home-page: https://github.com/pratik141/nsedt
Author: Pratik Anand
Classifier: Development Status :: 4 - Beta
Classifier: Intended Audience :: Developers
Classifier: License :: OSI Approved :: MIT License
Classifier: Programming Language :: Python :: 3
Classifier: Programming Language :: Python :: 3.9
Classifier: Programming Language :: Python :: 3.10
Classifier: Programming Language :: Python :: 3.11
License-File: LICENSE
Requires-Dist: requests
Requires-Dist: numpy
Requires-Dist: pandas
Requires-Dist: Deprecated
Requires-Dist: fake-http-header
Dynamic: author
Dynamic: classifier
Dynamic: description
Dynamic: description-content-type
Dynamic: home-page
Dynamic: license-file
Dynamic: requires-dist
Dynamic: summary
